Trees/AVLTree.py
Trees/BST.py
Trees/BinaryTree.py
Trees/Heap.py
cs_46_Curtis_trees-1.0.0.dist-info/DESCRIPTION.rst
cs_46_Curtis_trees-1.0.0.dist-info/METADATA
cs_46_Curtis_trees-1.0.0.dist-info/RECORD
cs_46_Curtis_trees-1.0.0.dist-info/WHEEL
cs_46_Curtis_trees-1.0.0.dist-info/metadata.json
cs_46_Curtis_trees-1.0.0.dist-info/top_level.txt
